pytest_mongodb_ry/__init__.py
pytest_mongodb_ry/plugin.py
pytest_mongodb_ry-1.1.42.dist-info/METADATA
pytest_mongodb_ry-1.1.42.dist-info/WHEEL
pytest_mongodb_ry-1.1.42.dist-info/entry_points.txt
pytest_mongodb_ry-1.1.42.dist-info/top_level.txt
pytest_mongodb_ry-1.1.42.dist-info/RECORD
