Metadata-Version: 2.4
Name: pytest-mongodb-ry
Version: 1.1.42
Summary: pytest plugin for MongoDB 
Author-email: Xue hy <ryhn0412@163.com>
Classifier: Programming Language :: Python
Classifier: Programming Language :: Python :: 3
Classifier: Framework :: Pytest
Classifier: Topic :: Database
Classifier: Topic :: Software Development :: Libraries
Requires-Dist: pymongo
